{"skeleton":{"hash":"h8jDQOm6yyFh0gX+kzNjcaJCiio","spine":"3.8.75","x":-323.98,"y":-66.95,"width":738.68,"height":703.94,"images":"../../../ps拆分/传说中的喵星解忧铺/spine/怪物/永久保鲜仙/images/","audio":"E:/qiaoba/ps拆分/传说中的喵星解忧铺/spine/怪物/永久保鲜仙"},"bones":[{"name":"root"},{"name":"box","parent":"root","x":-0.85,"y":24.26},{"name":"bone","parent":"box","length":196.96,"rotation":94.53,"x":-295.82,"y":149.46,"scaleX":1.0623},{"name":"bone2","parent":"bone","x":285.4,"y":-52.83},{"name":"bone3","parent":"bone","x":206.87,"y":-349.81},{"name":"bone4","parent":"bone","x":-342.52,"y":-335.08},{"name":"vegetable","parent":"box","length":44.85,"rotation":144.46,"x":4.12,"y":54.52},{"name":"vegetable2","parent":"vegetable","length":49.39,"rotation":-1.66,"x":44.85},{"name":"vegetable4","parent":"vegetable2","length":38.3,"rotation":-3.79,"x":47.97,"y":-0.48},{"name":"vegetable5","parent":"vegetable4","length":83.8,"rotation":-4.93,"x":38.3},{"name":"vegetable3","parent":"vegetable5","length":77.56,"rotation":-10.3,"x":82.77,"y":1.66},{"name":"body","parent":"box","x":54.36,"y":181.55},{"name":"body3","parent":"body","length":38.44,"rotation":-87.17,"x":0.95,"y":-1.9},{"name":"body4","parent":"body3","length":51.38,"rotation":-40.33,"x":38.44},{"name":"body5","parent":"body","length":31.68,"rotation":128.93,"x":-0.95,"y":3.32},{"name":"body2","parent":"body5","length":36.79,"rotation":-0.73,"x":30.42,"y":-0.81},{"name":"body6","parent":"body2","length":39.02,"rotation":11.73,"x":36.79},{"name":"body7","parent":"body6","length":56.09,"rotation":-1.16,"x":39.02},{"name":"eye","parent":"body7","length":20.56,"rotation":-48.05,"x":87.93,"y":55.46},{"name":"nose","parent":"body7","x":48.74,"y":57.68},{"name":"back1","parent":"box","length":140.17,"rotation":-10.27,"x":-119.11,"y":361.97},{"name":"line","parent":"box","length":28.62,"rotation":-33.69,"x":244.64,"y":222.74},{"name":"line2","parent":"line","length":25.77,"rotation":29.48,"x":28.62},{"name":"line3","parent":"line2","length":28.61,"rotation":19.53,"x":25.77},{"name":"line5","parent":"line3","length":23.21,"rotation":21.73,"x":28.15,"y":-0.26},{"name":"line6","parent":"line5","length":25.06,"rotation":41.63,"x":23.21},{"name":"line7","parent":"line6","length":16.57,"rotation":56.31,"x":25.06},{"name":"line4","parent":"line7","length":28.6,"rotation":15.72,"x":17.37,"y":0.27},{"name":"line8","parent":"line4","length":36.23,"rotation":-37.37,"x":28.6},{"name":"line10","parent":"line8","length":25.56,"rotation":-74.96,"x":34.49,"y":-2.13},{"name":"line11","parent":"line10","length":18.29,"rotation":-31.27,"x":25.56},{"name":"line12","parent":"line11","length":62.83,"rotation":-22.83,"x":18.75,"y":0.7},{"name":"arm","parent":"body6","length":54.1,"rotation":16.2,"x":8.12,"y":59.93},{"name":"box2","parent":"box","x":-345.68,"y":102.38,"color":"abe323ff"}],"slots":[{"name":"line","bone":"line10","attachment":"line"},{"name":"back2","bone":"box","attachment":"back2"},{"name":"back1","bone":"back1","attachment":"back1"},{"name":"body","bone":"body2","attachment":"body"},{"name":"nose","bone":"nose","attachment":"nose"},{"name":"vegetable","bone":"vegetable3","attachment":"vegetable"},{"name":"eye","bone":"eye","attachment":"eye"},{"name":"eye2","bone":"eye","attachment":"eye2"},{"name":"teer","bone":"eye","attachment":"teer"},{"name":"arm","bone":"arm","attachment":"arm"},{"name":"box","bone":"box","attachment":"box"},{"name":"door","bone":"bone","attachment":"door"}],"transform":[{"name":"box2","bones":["bone3"],"target":"box2","rotateMix":0,"translateMix":0.403,"scaleMix":0,"shearMix":0},{"name":"box2.1","order":1,"bones":["bone4"],"target":"box2","rotateMix":0,"translateMix":0.403,"scaleMix":0,"shearMix":0}],"skins":[{"name":"default","attachments":{"box":{"box":{"x":3.55,"y":293.73,"width":616,"height":638}},"arm":{"arm":{"x":26.72,"y":0.99,"rotation":-156.12,"width":86,"height":53}},"nose":{"nose":{"x":0.01,"y":0.13,"rotation":-138.77,"width":20,"height":16}},"eye2":{"eye2":{"x":-4.17,"y":-46.37,"rotation":-90.72,"width":97,"height":26}},"teer":{"teer":{"x":-5.19,"y":-47.86,"rotation":-90.72,"width":112,"height":30}},"vegetable":{"vegetable":{"type":"mesh","uvs":[0.72498,1,0.56102,0.99649,0.42858,0.95414,0.31979,0.93397,0.12429,0.75046,0,0.51452,0,0.38545,0.18263,0.09103,0.3734,0.11523,0.48534,0.30075,0.58467,0.5246,0.65404,0.61938,0.73129,0.76256,0.7439,0.87952,0.77228,0.92187],"triangles":[3,4,10,9,5,8,9,4,5,8,6,7,8,5,6,4,9,10,12,2,11,11,2,10,2,3,10,13,1,12,12,1,2,0,13,14,0,1,13],"vertices":[4,6,-1.62,15.08,0.99752,7,-46.89,13.73,0.00248,8,-95.59,7.92,0,10,-212.42,-43.96,0,5,6,51.78,48.94,0.14178,7,5.5,49.12,0.82975,8,-45.65,46.69,0.02116,9,-87.66,39.3,0.00209,10,-174.41,6.57,0.00523,4,7,53.82,69.79,0.51112,8,1.2,70.51,0.25703,9,-43.03,67.06,0.13734,10,-135.46,41.86,0.09452,4,7,90.85,90.28,0.21208,8,36.79,93.4,0.21502,9,-9.53,92.92,0.2951,10,-107.13,73.29,0.2778,4,7,184.2,91.79,0.00953,8,129.84,101.07,0.01398,9,82.51,108.56,0.07116,10,-19.36,105.13,0.90533,1,10,66.27,105.41,1,1,10,98.56,83.8,1,2,9,209.47,-45.66,0.01087,10,133.11,-23.92,0.98913,2,9,153.14,-93.35,0.21712,10,86.22,-80.91,0.78288,3,8,113.69,-92.28,0.04009,9,83.04,-85.46,0.70394,10,15.84,-85.67,0.25597,2,8,40.63,-66.5,0.58266,9,8.04,-66.06,0.41734,5,6,88.61,-64.24,1.0E-5,7,45.6,-62.95,0.08594,8,1.76,-62.48,0.87578,9,-31.04,-65.39,0.03827,10,-99.99,-86.32,0,4,6,39.36,-46.46,0.23167,7,-4.15,-46.6,0.46544,8,-48.96,-49.46,0.30289,10,-152.35,-87.07,0,4,6,14.94,-20.63,0.90357,7,-29.3,-21.49,0.06792,8,-75.71,-26.07,0.02851,10,-184.31,-71.53,0,4,6,-1.36,-16.61,0.99753,7,-45.71,-17.95,6.3E-4,8,-92.32,-23.61,0.00184,10,-200.98,-73.52,0],"hull":15,"edges":[0,2,2,4,4,6,6,8,8,10,10,12,12,14,14,16,16,18,18,20,20,22,22,24,24,26,26,28,0,28,2,24,4,22,6,20,8,18,10,16],"width":385,"height":301}},"body":{"body":{"type":"mesh","uvs":[0.13902,0.03804,0.15747,0.09704,0.09814,0.16049,0.07751,0.26297,0.1033,0.36302,0.20391,0.4045,0.22748,0.44964,0.30967,0.60703,0.45671,0.74368,0.61148,0.76564,0.62908,0.80406,0.5813,0.8112,0.56873,0.87066,0.62908,0.9646,0.70199,1,0.75102,0.99195,0.78747,0.9646,0.8717,0.95628,0.96976,0.87898,1,0.79811,1,0.51033,0.92953,0.38071,0.8453,0.29866,0.70576,0.24514,0.65925,0.15595,0.67056,0.09649,0.62405,0.0406,0.55365,0.05606,0.47822,0.01801,0.40153,0,0.30599,0.00612,0.25319,0.02276,0.22428,0,0.16142,0],"triangles":[32,1,0,32,0,33,31,1,32,25,27,26,24,27,25,2,5,3,5,4,3,5,1,31,1,5,2,5,31,30,5,30,29,5,29,28,5,28,27,5,27,24,5,24,23,6,5,23,7,6,23,7,23,22,8,22,21,20,9,21,8,7,22,9,8,21,9,20,19,10,9,19,18,10,19,17,10,18,16,13,10,12,11,10,13,12,10,17,16,10,16,14,13,15,14,16],"vertices":[1,17,119.3,9.08,1,2,14,206.78,41.59,1.0E-5,17,105.83,17.59,0.99999,2,14,203.13,63.22,0.00129,17,105.93,39.53,0.99871,3,14,185.66,83.84,0.00853,16,132.51,60.95,8.3E-4,17,92.24,62.83,0.99065,4,12,-79.72,-173.73,2.0E-5,14,161.53,95.2,0.02287,16,110.99,76.71,0.01071,17,70.4,78.15,0.9664,5,13,15.88,-182.82,2.0E-5,12,-67.77,-149.64,0.00171,14,137.68,82.78,0.07069,16,85.22,69.06,0.06334,17,44.79,69.98,0.86425,6,13,21.64,-171.12,5.2E-4,12,-55.81,-144.45,0.00522,14,124.96,85.63,0.1284,15,93.43,87.63,4.3E-4,16,73.27,74.29,0.12405,17,32.74,74.97,0.74138,6,13,41.72,-130.33,0.01596,12,-14.1,-126.35,0.03487,14,80.59,95.58,0.365,15,48.94,97.02,0.01461,16,31.62,92.52,0.2404,17,-9.28,92.35,0.32916,6,13,47.86,-80.2,0.08924,12,23.02,-92.12,0.11108,14,30.43,89.79,0.55243,15,-1.15,90.59,0.01451,16,-18.73,96.42,0.15028,17,-59.69,95.23,0.08245,6,13,29.29,-46.66,0.36295,12,30.57,-54.52,0.20487,14,2.17,63.87,0.37885,15,-29.07,64.31,0.00143,16,-51.41,76.36,0.04,17,-91.96,74.51,0.0119,5,13,34.56,-37.18,0.68951,12,40.72,-50.71,0.13531,14,-8.27,66.77,0.16218,16,-61.12,81.2,0.01089,17,-101.76,79.15,0.00211,5,13,43.15,-45.34,0.8353,12,41.99,-62.49,0.07338,14,-2.36,77.03,0.08713,16,-53.35,90.14,0.00386,17,-94.18,88.26,3.3E-4,4,13,57.24,-38.41,0.90284,12,57.22,-66.32,0.04305,14,-12.4,89.11,0.05269,16,-60.91,103.91,0.00142,3,13,67.54,-11.86,0.99172,12,82.25,-52.76,0.00271,14,-40.62,92.89,0.00557,1,13,64.92,8.64,1,1,13,54.97,16.15,1,1,13,43.92,18.92,1,2,13,29.64,33.98,0.99715,12,83.03,6.72,0.00285,2,13,-0.87,40.85,0.74747,12,64.22,31.7,0.25253,2,13,-21.99,33.98,0.37072,12,43.67,40.13,0.62928,3,12,-30.78,43.81,0.17751,14,-6.19,-51.73,0.43308,15,-35.96,-51.38,0.3894,4,12,-65.16,28.22,0.00298,14,30.77,-59.4,0.18366,15,1.1,-58.58,0.78292,16,-46.86,-50.1,0.03045,4,14,60.27,-56.69,0.02769,15,30.56,-55.5,0.78207,16,-17.39,-53.08,0.18957,17,-55.32,-54.21,6.7E-4,3,15,62.59,-37.21,0.21482,16,17.7,-41.67,0.60127,17,-20.48,-42.1,0.1839,3,15,87.79,-42.53,0.01045,16,41.29,-52.01,0.31682,17,3.32,-51.96,0.67273,3,15,98.18,-54.24,1.4E-4,16,49.08,-65.58,0.2008,17,11.38,-65.37,0.79905,2,16,67.12,-69.32,0.14994,17,29.49,-68.74,0.85006,2,16,77.74,-55.16,0.08901,17,39.83,-54.36,0.91099,2,16,98.23,-50.8,0.01621,17,60.22,-49.59,0.98379,2,16,115.61,-42.28,9.1E-4,17,77.42,-40.72,0.99909,1,17,93.98,-24.1,1,1,17,100.87,-12.33,1,1,17,110.08,-12.1,1,1,17,121.67,-1.94,1],"hull":34,"edges":[0,2,2,4,4,6,6,8,8,10,14,16,16,18,18,20,20,22,22,24,24,26,26,28,28,30,30,32,32,34,34,36,36,38,38,40,40,42,42,44,44,46,46,48,48,50,50,52,52,54,54,56,56,58,58,60,60,62,62,64,64,66,0,66,10,46,10,12,12,14,12,46,14,44,16,42,18,40,18,38,20,36,2,62,54,48],"width":245,"height":259}},"back1":{"back1":{"x":69.77,"y":-84.15,"rotation":10.27,"width":448,"height":360}},"back2":{"back2":{"x":-12.45,"y":256.73,"width":558,"height":552}},"door":{"door":{"type":"mesh","uvs":[0.05841,0.61453,0.42696,0.84909,0.75501,1,1,1,1,0.84909,0.92916,0.34621,0.88056,0.30178,0.26901,0,0.11916,0,0.05387,0.01279,0,0.06367,0,0.316,0.74286,0.37464],"triangles":[12,11,10,0,11,12,1,0,12,9,8,7,12,9,7,9,12,10,12,7,6,12,6,5,12,5,4,2,1,12,4,2,12,2,4,3],"vertices":[3,5,207.64,196.43,0.03168,4,-133.84,205.93,0.00808,2,-34.9,14.78,0.96024,3,5,72.76,118.38,0.6044,4,-268.73,127.88,0.07318,2,-169.79,-63.26,0.32242,3,5,-15.75,46.42,0.97222,4,-357.24,55.91,0.00455,2,-258.3,-135.23,0.02323,1,5,-20.39,-12.2,1,3,5,61.9,-18.72,0.83882,4,-279.59,-9.22,0.06612,2,-180.65,-200.36,0.09505,2,5,337.46,-23.49,0.00269,4,-4.03,-13.99,0.99731,3,4,21.11,-4.28,0.96568,3,-165.35,-142.59,0.00925,2,120.05,-195.43,0.02508,2,4,197.26,129,0.001,3,10.8,-9.31,0.999,2,3,13.87,29.44,0.93636,2,299.27,-23.39,0.06364,3,4,184.64,181.36,2.0E-5,3,-1.82,43.05,0.82833,2,283.58,-9.78,0.17165,2,3,-18.82,57.8,0.66021,2,266.58,4.96,0.33979,1,2,128.99,15.86,1,4,5,325.48,22.31,0.0129,4,-16,31.81,0.84809,3,-202.47,-106.5,0.0043,2,82.94,-159.33,0.13471],"hull":12,"edges":[0,2,2,4,4,6,6,8,8,10,10,12,12,14,14,16,20,22,0,22,16,18,18,20,18,24,24,10,24,4],"width":240,"height":547}},"eye":{"eye":{"x":-1.71,"y":-48.9,"rotation":-90.72,"width":96,"height":39}},"line":{"line":{"type":"mesh","uvs":[0.08556,0.67257,0.18931,0.717,0.31217,0.742,0.43504,0.71145,0.47326,0.65868,0.33675,0.58925,0.20296,0.43096,0.20842,0.1949,0.405,0.06437,0.54152,0.05604,0.68077,0,0.83913,0.01994,0.95107,0.12825,1,0.29765,0.96745,0.52538,0.79817,0.54482,0.62889,0.42818,0.57975,0.30321,0.47599,0.3282,0.43902,0.34897,0.44974,0.36957,0.5998,0.45316,0.71533,0.56097,0.74273,0.66758,0.68437,0.82866,0.53668,0.94617,0.33659,1,0.16985,0.98978,0.01144,0.87954,0,0.72085],"triangles":[14,15,13,13,15,16,13,17,12,12,17,11,11,17,10,16,17,13,18,9,17,18,8,9,17,9,10,18,19,8,20,6,19,20,5,6,6,7,19,19,7,8,21,4,20,4,5,20,4,21,22,24,4,23,4,22,23,25,3,24,3,4,24,26,3,25,26,2,3,27,2,26,27,1,2,27,28,1,28,0,1,28,29,0],"vertices":[2,21,-2.27,18.07,0.97711,22,-17.99,30.93,0.02289,3,21,17.41,21.84,0.64918,22,0.99,24.53,0.33317,23,-15.16,31.4,0.01765,6,21,38.04,30.33,0.05322,22,23.13,21.77,0.4831,23,4.78,21.4,0.43295,24,-13.68,28.78,0.02473,25,-8.45,46.02,0.0032,27,16.64,50.52,0.00279,5,22,44.54,28.71,0.02801,23,27.29,20.78,0.33549,24,6.99,19.87,0.38918,25,1.08,25.62,0.14682,27,0.18,35.16,0.1005,6,22,50.65,38.41,7.5E-4,23,36.29,27.89,0.0416,24,17.99,23.14,0.17871,25,11.47,20.76,0.30074,26,9.74,22.82,0.01194,27,-1.24,23.78,0.46626,4,24,5.92,47.48,0.00269,25,18.62,46.97,0.01593,27,25.9,25.06,0.81196,28,-17.36,18.28,0.16943,2,27,60.22,12.55,0.00605,28,17.51,29.16,0.99395,2,28,55.05,11.89,0.96153,29,-8.21,23.5,0.03847,4,28,62.15,-29.29,0.03897,29,33.41,19.67,0.40722,30,-3.5,20.88,0.3182,31,-28.34,9.96,0.23561,2,30,20.79,19.31,0.0209,31,-5.35,17.94,0.9791,1,31,15.86,34.09,1,1,31,43.94,38.37,1,1,31,68.25,25.52,1,1,31,84.66,-0.67,1,2,30,85.83,-71.59,0.00901,31,89.88,-40.6,0.99099,2,30,55.51,-71.23,0.04254,31,61.79,-52.03,0.95746,3,29,25.1,-54.98,3.4E-4,30,28.14,-47.24,0.19332,31,27.26,-40.54,0.80634,4,28,11.45,-41.27,0.00606,29,31.83,-32.41,0.06255,30,22.18,-24.45,0.55905,31,12.91,-21.85,0.37234,5,27,26.62,-26.9,0.016,28,14.75,-22.59,0.16734,29,14.63,-24.37,0.36797,30,3.31,-26.5,0.44669,31,-3.68,-31.07,0.002,4,27,30.58,-20.52,0.11131,28,14.03,-15.1,0.45931,29,7.22,-23.13,0.2709,30,-3.67,-29.29,0.15849,4,27,27.16,-18.3,0.31436,28,9.96,-15.42,0.48828,29,6.48,-27.14,0.12891,30,-2.23,-33.1,0.06845,3,26,19.24,-18.54,0.62235,27,-3.3,-18.61,0.37614,28,-14.06,-34.15,0.00151,2,25,36.69,-18.14,0.46909,26,-8.64,-19.74,0.53091,3,24,55.33,-7.01,0.0031,25,19.35,-26.58,0.90708,26,-25.28,-9.99,0.08982,2,24,30.05,-23.25,0.56624,25,-10.33,-21.92,0.43376,2,23,33.88,-23.62,0.43243,24,-3.32,-23.82,0.56757,2,22,30.77,-22.94,0.49805,23,-2.96,-23.29,0.50195,2,21,41.01,-19.8,0.15572,22,1.04,-23.33,0.84428,2,21,6.85,-19.39,0.99902,22,-28.5,-6.16,9.8E-4,1,21,-10.25,2.59,1],"hull":30,"edges":[0,2,2,4,4,6,6,8,8,10,10,12,12,14,14,16,16,18,18,20,20,22,22,24,24,26,26,28,28,30,30,32,32,34,34,36,36,38,38,40,40,42,42,44,44,46,46,48,48,50,50,52,52,54,54,56,56,58,0,58,4,52,2,54,6,50,8,48,8,44,8,42,10,40,14,38,36,16,18,34],"width":178,"height":175}}}}],"animations":{"Hit":{"slots":{"eye":{"color":[{"time":0.1,"color":"ffffffff"},{"time":0.2,"color":"ffffff00","curve":"stepped"},{"time":0.4,"color":"ffffff00"},{"time":0.5,"color":"ffffffff"}]},"teer":{"color":[{"color":"ffffff00"}]},"eye2":{"color":[{"color":"ffffff00","curve":"stepped"},{"time":0.1,"color":"ffffff00"},{"time":0.2,"color":"ffffffff","curve":"stepped"},{"time":0.4,"color":"ffffffff"},{"time":0.5,"color":"ffffff00"}]}},"bones":{"vegetable3":{"rotate":[{"angle":-0.61}]},"vegetable5":{"rotate":[{"angle":-0.67}]},"arm":{"rotate":[{"angle":14.07,"curve":"stepped"},{"time":0.1,"angle":14.07,"curve":0.25,"c3":0.75},{"time":0.2,"angle":-0.74},{"time":0.4,"angle":44.19},{"time":0.6,"angle":14.07}]},"body2":{"rotate":[{"angle":0.72}]},"line5":{"rotate":[{"angle":3.05,"curve":"stepped"},{"time":0.1,"angle":3.05,"curve":0.25,"c3":0.75},{"time":0.2,"angle":-5.42},{"time":0.4,"angle":12.06},{"time":0.5,"angle":7.55},{"time":0.6,"angle":3.05}]},"line6":{"rotate":[{"angle":2.77,"curve":"stepped"},{"time":0.1,"angle":2.77,"curve":0.25,"c3":0.75},{"time":0.2,"angle":-5.7},{"time":0.4,"angle":11.78},{"time":0.5,"angle":7.27},{"time":0.6,"angle":2.77}]},"body6":{"rotate":[{"angle":0.67}]},"vegetable2":{"rotate":[{"angle":-0.83}]},"line12":{"rotate":[{"angle":-3.36,"curve":"stepped"},{"time":0.1,"angle":-3.36,"curve":0.25,"c3":0.75},{"time":0.2,"angle":26.26},{"time":0.4,"angle":-6.18},{"time":0.6,"angle":-3.36}]},"vegetable4":{"rotate":[{"angle":-0.74}]},"box":{"translate":[{"time":0.1,"curve":0.25,"c3":0.75},{"time":0.2,"y":-6.23},{"time":0.4,"y":10.39},{"time":0.5}],"scale":[{"y":0.973,"curve":"stepped"},{"time":0.1,"y":0.973,"curve":0.25,"c3":0.75},{"time":0.2,"y":0.529},{"time":0.4,"y":1.004},{"time":0.5,"y":0.954,"curve":0.25,"c3":0.75},{"time":0.6,"y":0.973}]},"vegetable":{"rotate":[{"time":0.1,"curve":0.25,"c3":0.75},{"time":0.2,"angle":-15.04},{"time":0.4,"angle":10.46},{"time":0.6}],"translate":[{"time":0.1,"curve":0.25,"c3":0.75},{"time":0.2,"x":-66.77,"y":-44.83},{"time":0.4,"y":49.59},{"time":0.6}]},"line4":{"rotate":[{"angle":3.81}]},"line8":{"rotate":[{"angle":-2.75,"curve":"stepped"},{"time":0.1,"angle":-2.75,"curve":0.25,"c3":0.75},{"time":0.2,"angle":26.87},{"time":0.4,"angle":-5.56},{"time":0.6,"angle":-2.75}]},"nose":{"translate":[{"x":-0.75,"y":0.97}]},"line11":{"rotate":[{"angle":-3.79,"curve":"stepped"},{"time":0.1,"angle":-3.79,"curve":0.25,"c3":0.75},{"time":0.2,"angle":25.84},{"time":0.4,"angle":-6.6},{"time":0.6,"angle":-3.79}]},"line10":{"rotate":[{"angle":-3.79,"curve":"stepped"},{"time":0.1,"angle":-3.79,"curve":0.25,"c3":0.75},{"time":0.2,"angle":25.84},{"time":0.4,"angle":-6.6},{"time":0.6,"angle":-3.79}]},"body5":{"rotate":[{"angle":0.77}]},"body7":{"rotate":[{"angle":0.63,"curve":"stepped"},{"time":0.1,"angle":0.63,"curve":0.25,"c3":0.75},{"time":0.2,"angle":-18.18},{"time":0.4,"angle":14.06},{"time":0.6,"angle":0.63}]},"line2":{"rotate":[{"angle":3.81,"curve":"stepped"},{"time":0.1,"angle":3.81,"curve":0.25,"c3":0.75},{"time":0.2,"angle":-4.66},{"time":0.4,"angle":12.82},{"time":0.5,"angle":8.31},{"time":0.6,"angle":3.81}]},"body":{"rotate":[{"time":0.1,"curve":0.25,"c3":0.75},{"time":0.2,"angle":-10.34},{"time":0.4}],"translate":[{"time":0.1,"curve":0.25,"c3":0.75},{"time":0.2,"x":-15.09,"y":-51.92},{"time":0.4,"y":13.67,"curve":0.25,"c3":0.75},{"time":0.5,"y":17.26},{"time":0.6}]},"line7":{"rotate":[{"angle":3.05}]},"line3":{"rotate":[{"angle":3.38,"curve":"stepped"},{"time":0.1,"angle":3.38,"curve":0.25,"c3":0.75},{"time":0.2,"angle":-5.08},{"time":0.4,"angle":12.39},{"time":0.5,"angle":7.89},{"time":0.6,"angle":3.38}]},"back1":{"rotate":[{"time":0.1,"curve":0.25,"c3":0.75},{"time":0.2,"angle":-6.16},{"time":0.4,"angle":7.5},{"time":0.6}],"translate":[{"x":2.34,"y":-0.8,"curve":"stepped"},{"time":0.1,"x":2.34,"y":-0.8,"curve":0.25,"c3":0.75},{"time":0.2,"x":28.19,"y":-13.03},{"time":0.4,"x":21.73,"y":-4.45},{"time":0.6,"x":2.34,"y":-0.8}]},"box2":{"translate":[{"x":-88.28,"y":-16.45,"curve":"stepped"},{"time":0.1,"x":-88.28,"y":-16.45,"curve":0.25,"c3":0.75},{"time":0.2,"x":-264.11,"y":-181.11},{"time":0.4,"x":334.4,"y":103.76},{"time":0.5,"x":14.72,"y":-11.68},{"time":0.6,"x":-88.28,"y":-16.45}]}}},"Idle":{"slots":{"teer":{"color":[{"color":"ffffff00"}]},"eye2":{"color":[{"color":"ffffff00"}]}},"bones":{"back1":{"translate":[{"x":2.34,"y":-0.8,"curve":0.25,"c3":0.75},{"time":0.7,"curve":0.25,"c3":0.75},{"time":1.5,"x":2.68,"y":-0.92,"curve":0.25,"c3":0.75},{"time":1.6,"x":2.38,"y":-0.82}]},"line3":{"rotate":[{"angle":3.38,"curve":0.25,"c3":0.75},{"time":0.1,"angle":3.81,"curve":0.25,"c3":0.75},{"time":0.9,"curve":0.25,"c3":0.75},{"time":1.6,"angle":3.33}]},"line6":{"rotate":[{"angle":2.77,"curve":0.25,"c3":0.75},{"time":0.3,"angle":3.81,"curve":0.25,"c3":0.75},{"time":1.1,"curve":0.25,"c3":0.75},{"time":1.6,"angle":2.38}]},"line2":{"rotate":[{"angle":3.81,"curve":0.25,"c3":0.75},{"time":0.8,"curve":0.25,"c3":0.75},{"time":1.6,"angle":3.81}]},"eye":{"rotate":[{"time":0.5},{"time":0.6,"angle":-8.57},{"time":0.8}],"scale":[{"time":0.5},{"time":0.6,"x":0.177},{"time":0.8}]},"line10":{"rotate":[{"angle":-3.79,"curve":0.25,"c3":0.75},{"time":0.8,"curve":0.25,"c3":0.75},{"time":1.6,"angle":-3.79}]},"line8":{"rotate":[{"angle":-2.75,"curve":0.25,"c3":0.75},{"time":0.3,"angle":-3.79,"curve":0.25,"c3":0.75},{"time":1.1,"curve":0.25,"c3":0.75},{"time":1.6,"angle":-2.37}]},"line11":{"rotate":[{"angle":-3.79,"curve":0.25,"c3":0.75},{"time":0.8,"curve":0.25,"c3":0.75},{"time":1.6,"angle":-3.79}]},"body7":{"rotate":[{"angle":0.63,"curve":0.25,"c3":0.75},{"time":0.2667,"angle":0.84,"curve":0.25,"c3":0.75},{"time":1.0667,"curve":0.25,"c3":0.75},{"time":1.1,"angle":0.63},{"time":1.2,"angle":-2.4},{"time":1.3,"angle":3.18},{"time":1.4,"angle":-3.12},{"time":1.5,"angle":0.63},{"time":1.6,"angle":0.56}]},"box":{"scale":[{"y":0.973,"curve":0.25,"c3":0.75},{"time":0.8,"curve":0.25,"c3":0.75},{"time":1.6,"y":0.973}]},"body2":{"rotate":[{"angle":0.72,"curve":0.25,"c3":0.75},{"time":0.1333,"angle":0.84,"curve":0.25,"c3":0.75},{"time":0.9333,"curve":0.25,"c3":0.75},{"time":1.6,"angle":0.7}]},"line12":{"rotate":[{"angle":-3.36,"curve":0.25,"c3":0.75},{"time":0.1,"angle":-3.79,"curve":0.25,"c3":0.75},{"time":0.9,"curve":0.25,"c3":0.75},{"time":1.6,"angle":-3.31}]},"vegetable5":{"rotate":[{"angle":-0.67,"curve":0.25,"c3":0.75},{"time":0.2,"angle":-0.83,"curve":0.25,"c3":0.75},{"time":1,"curve":0.25,"c3":0.75},{"time":1.6,"angle":-0.63}]},"vegetable4":{"rotate":[{"angle":-0.74,"curve":0.25,"c3":0.75},{"time":0.1,"angle":-0.83,"curve":0.25,"c3":0.75},{"time":0.9,"curve":0.25,"c3":0.75},{"time":1.6,"angle":-0.73}]},"vegetable2":{"rotate":[{"angle":-0.83,"curve":0.25,"c3":0.75},{"time":0.8,"curve":0.25,"c3":0.75},{"time":1.6,"angle":-0.83}]},"body5":{"rotate":[{"angle":0.77,"curve":0.25,"c3":0.75},{"time":0.0667,"angle":0.84,"curve":0.25,"c3":0.75},{"time":0.8667,"curve":0.25,"c3":0.75},{"time":1.6,"angle":0.77}]},"body6":{"rotate":[{"angle":0.67,"curve":0.25,"c3":0.75},{"time":0.2,"angle":0.84,"curve":0.25,"c3":0.75},{"time":1,"curve":0.25,"c3":0.75},{"time":1.6,"angle":0.63}]},"vegetable3":{"rotate":[{"angle":-0.61,"curve":0.25,"c3":0.75},{"time":0.3,"angle":-0.83,"curve":0.25,"c3":0.75},{"time":1.1,"curve":0.25,"c3":0.75},{"time":1.6,"angle":-0.52}]},"arm":{"rotate":[{"angle":14.07,"curve":0.25,"c3":0.75},{"time":0.1667,"angle":17,"curve":0.25,"c3":0.75},{"time":0.9667,"curve":0.25,"c3":0.75},{"time":1.6,"angle":13.46}]},"line5":{"rotate":[{"angle":3.05,"curve":0.25,"c3":0.75},{"time":0.2,"angle":3.81,"curve":0.25,"c3":0.75},{"time":1,"curve":0.25,"c3":0.75},{"time":1.6,"angle":2.86}]},"line4":{"rotate":[{"angle":3.81,"curve":0.25,"c3":0.75},{"time":0.8,"curve":0.25,"c3":0.75},{"time":1.6,"angle":3.81}]},"line7":{"rotate":[{"angle":3.05,"curve":0.25,"c3":0.75},{"time":0.2,"angle":3.81,"curve":0.25,"c3":0.75},{"time":1,"curve":0.25,"c3":0.75},{"time":1.6,"angle":2.86}]},"nose":{"translate":[{"x":-0.75,"y":0.97,"curve":0.25,"c3":0.75},{"time":0.8,"curve":0.25,"c3":0.75},{"time":1.1,"x":-0.75,"y":0.97},{"time":1.2,"x":2.13,"y":-2.7},{"time":1.3,"x":-0.75,"y":0.97},{"time":1.4,"x":3.9,"y":-4.9},{"time":1.5,"x":-0.75,"y":0.97}]},"box2":{"translate":[{"x":-88.28,"y":-16.45,"curve":0.25,"c3":0.75},{"time":0.1,"x":-99.32,"y":-18.51,"curve":0.25,"c3":0.75},{"time":0.9,"curve":0.25,"c3":0.75},{"time":1.6,"x":-86.91,"y":-16.2}]}}},"OnDead":{"slots":{"nose":{"color":[{"time":1.1,"color":"ffffffff"},{"time":1.2,"color":"ffffff00"}]},"body":{"color":[{"time":1.1,"color":"ffffffff"},{"time":1.2,"color":"ffffff00"}]},"vegetable":{"color":[{"color":"ffffffff"},{"time":0.3,"color":"2e519cff","curve":"stepped"},{"time":1.1,"color":"2e519cff"},{"time":1.2,"color":"2e519c00"}]},"line":{"color":[{"time":1.1,"color":"ffffffff"},{"time":1.2,"color":"ffffff00"}]},"eye":{"color":[{"time":0.7,"color":"ffffffff"},{"time":0.8,"color":"ffffff00"}]},"arm":{"color":[{"time":1,"color":"ffffffff"},{"time":1.1,"color":"ffffff00"}]},"back2":{"color":[{"time":1.1,"color":"ffffffff"},{"time":1.2,"color":"ffffff00"}]},"teer":{"color":[{"color":"ffffff00","curve":"stepped"},{"time":0.7,"color":"ffffff00"},{"time":0.8,"color":"ffffffff","curve":"stepped"},{"time":1,"color":"ffffffff"},{"time":1.1,"color":"ffffff00"}]},"eye2":{"color":[{"color":"ffffff00","curve":"stepped"},{"time":0.7,"color":"ffffff00"},{"time":0.8,"color":"ffffffff","curve":"stepped"},{"time":1,"color":"ffffffff"},{"time":1.1,"color":"ffffff00"}]},"back1":{"color":[{"color":"ffffffff"},{"time":0.4,"color":"2e519cff","curve":"stepped"},{"time":1.1,"color":"2e519cff"},{"time":1.2,"color":"2e519c00"}]},"door":{"color":[{"time":1.1,"color":"ffffffff"},{"time":1.2,"color":"ffffff00"}]},"box":{"color":[{"time":1.1,"color":"ffffffff"},{"time":1.2,"color":"ffffff00"}]}},"bones":{"vegetable3":{"rotate":[{"angle":-0.61}]},"vegetable5":{"rotate":[{"angle":-0.67}]},"arm":{"rotate":[{"angle":14.07,"curve":0.25,"c3":0.75},{"time":0.3,"angle":75.31},{"time":0.5,"angle":87.43},{"time":0.6,"angle":75.31},{"time":0.7,"angle":87.43,"curve":"stepped"},{"time":0.8,"angle":87.43},{"time":1,"angle":66.17}],"translate":[{"curve":0.25,"c3":0.75},{"time":0.3,"x":-26.96,"y":-15.42}],"scale":[{"time":0.3,"curve":0.25,"c3":0.75},{"time":0.5,"x":1.208},{"time":0.6,"curve":0.25,"c3":0.75},{"time":0.7,"x":1.208,"curve":"stepped"},{"time":0.8,"x":1.208},{"time":1,"x":1.791},{"time":1.1,"x":0.825}]},"body2":{"rotate":[{"angle":0.72,"curve":0.25,"c3":0.75},{"time":0.3,"angle":-11.83}]},"line5":{"rotate":[{"angle":3.05}]},"line6":{"rotate":[{"angle":2.77}]},"body6":{"rotate":[{"angle":0.67,"curve":0.25,"c3":0.75},{"time":0.3,"angle":-11.87}]},"vegetable2":{"rotate":[{"angle":-0.83}]},"line12":{"rotate":[{"angle":-3.36}]},"vegetable4":{"rotate":[{"angle":-0.74}]},"box":{"rotate":[{"time":0.9,"curve":0.36,"c2":0.64,"c3":0.695},{"time":1,"angle":1.83},{"time":1.1,"angle":-15.21},{"time":1.2}],"translate":[{"time":1},{"time":1.1,"y":55.37},{"time":1.2}],"scale":[{"y":0.973,"curve":0.258,"c3":0.619,"c4":0.45},{"time":0.4,"y":1.004,"curve":0.349,"c2":0.39,"c3":0.722,"c4":0.85},{"time":0.9,"y":0.973}]},"line4":{"rotate":[{"angle":3.81}]},"line8":{"rotate":[{"angle":-2.75}]},"nose":{"translate":[{"x":-0.75,"y":0.97}]},"line11":{"rotate":[{"angle":-3.79}]},"line10":{"rotate":[{"angle":-3.79}]},"body5":{"rotate":[{"angle":0.77,"curve":0.25,"c3":0.75},{"time":0.3,"angle":-11.77,"curve":"stepped"},{"time":0.8,"angle":-11.77},{"time":1,"angle":8.11}]},"body7":{"rotate":[{"angle":0.63,"curve":0.25,"c3":0.75},{"time":0.3,"angle":29.13,"curve":"stepped"},{"time":0.8,"angle":29.13},{"time":0.9,"angle":33.55}]},"line2":{"rotate":[{"angle":3.81}]},"line7":{"rotate":[{"angle":3.05}]},"line3":{"rotate":[{"angle":3.38}]},"back1":{"translate":[{"x":2.34,"y":-0.8}]},"box2":{"translate":[{"x":-88.28,"y":-16.45,"curve":0.257,"c3":0.619,"c4":0.46},{"time":0.4,"x":-135.8,"y":-26.22,"curve":0.351,"c2":0.39,"c3":0.724,"c4":0.87},{"time":0.9,"x":-88.28,"y":-16.45,"curve":0.358,"c2":0.65,"c3":0.693},{"time":1,"x":-106.48,"y":-22.69},{"time":1.1,"x":439.28,"y":204.8}]}}}}}